cvutils/__init__.py
cvutils/resize_img.py
cvutils/resnet.py
cvutils/video2img.py
cvutils2-0.0.1.dist-info/METADATA
cvutils2-0.0.1.dist-info/WHEEL
cvutils2-0.0.1.dist-info/top_level.txt
cvutils2-0.0.1.dist-info/RECORD
